{
  "version": "0.1.0",
  "sourceId": "europe_pmc_oa",
  "updatedAt": "2026-06-12T14:38:28.122Z",
  "harvestRunId": "13176ea0-8036-4f26-9507-21f35bd6bfe7",
  "queries": [
    {
      "query": "(CASE REPORT) AND (OPEN_ACCESS:Y)",
      "specialties": ["internal_medicine", "pediatrics", "critical_care"],
      "hitCount": 2128167
    },
    {
      "query": "(intensive care OR critical care) AND (case report) AND (OPEN_ACCESS:Y)",
      "specialties": ["critical_care"],
      "hitCount": 250484
    }
  ],
  "documents": [
    {
      "id": "1844abf4-5305-488c-b4fd-51bbcfb0cbe9",
      "url": "https://europepmc.org/article/PMC/13248532",
      "title": "Adolescent Paraspinal Lipoblastoma: A Case Report",
      "journal": "J Orthop Case Rep",
      "publishedAt": "2026-06-01",
      "sourceLanguage": "und",
      "license": "europepmc-oa",
      "specialty": "pediatrics",
      "harvestedAt": "2026-06-12T14:38:28.122Z",
      "licenseVerified": true,
      "sourceId": "europe_pmc_oa",
      "pmcid": "PMC13248532",
      "searchQuery": "(CASE REPORT) AND (OPEN_ACCESS:Y)",
      "isOpenAccess": true,
      "inPmc": true,
      "authorString": "Bano J, Weiner S, Baccon J, Floccari L."
    },
    {
      "id": "12d490c0-e9f3-4ae5-a66f-e3ee59f446a3",
      "doi": "10.3389/fruro.2026.1811127",
      "url": "https://europepmc.org/article/PMC/13149272",
      "title": "Case Report: Isolated male epispadias in adult: a rare case report.",
      "journal": "Front Urol",
      "publishedAt": "2026-04-23",
      "sourceLanguage": "und",
      "license": "europepmc-oa",
      "specialty": "other",
      "harvestedAt": "2026-06-12T14:38:28.122Z",
      "licenseVerified": true,
      "sourceId": "europe_pmc_oa",
      "pmcid": "PMC13149272",
      "pmid": "42109823",
      "searchQuery": "(CASE REPORT) AND (OPEN_ACCESS:Y)",
      "isOpenAccess": true,
      "inPmc": true,
      "authorString": "Nofrian RA, Pitoyo J, Siregar S, Ciam A, Yudawa MF."
    },
    {
      "id": "3b3889b2-2b5d-40b7-9458-ebdbe2ddd421",
      "url": "https://europepmc.org/article/PMC/13226573",
      "title": "Case Report: Bimekizumab for dissecting cellulitis of the scalp",
      "journal": "Front Immunol",
      "publishedAt": "2026-06-04",
      "sourceLanguage": "und",
      "license": "europepmc-oa",
      "specialty": "other",
      "harvestedAt": "2026-06-12T14:38:28.122Z",
      "licenseVerified": true,
      "sourceId": "europe_pmc_oa",
      "pmcid": "PMC13226573",
      "searchQuery": "(CASE REPORT) AND (OPEN_ACCESS:Y)",
      "isOpenAccess": true,
      "inPmc": true,
      "authorString": "Seiter D."
    },
    {
      "id": "c7541ab3-4a10-4edd-84c3-3e18686b1827",
      "url": "https://europepmc.org/article/PMC/13199354",
      "title": "Vesicovaginal reflux: a case report and literature overview",
      "journal": "Front Pediatr",
      "publishedAt": "2026-05-27",
      "sourceLanguage": "und",
      "license": "europepmc-oa",
      "specialty": "other",
      "harvestedAt": "2026-06-12T14:38:28.122Z",
      "licenseVerified": true,
      "sourceId": "europe_pmc_oa",
      "pmcid": "PMC13199354",
      "searchQuery": "(CASE REPORT) AND (OPEN_ACCESS:Y)",
      "isOpenAccess": true,
      "inPmc": true,
      "authorString": "Wang Y, Sun S, Geng L, Wang Y, Li G, Xu X."
    },
    {
      "id": "329373b4-c7e1-4cb4-ae64-d2cfdd38a848",
      "doi": "10.1155/crra/7334537",
      "url": "https://europepmc.org/article/PMC/13191780",
      "title": "Klippel-Feil Syndrome: A Rare Case Report.",
      "journal": "Case Rep Radiol",
      "publishedAt": "2026-05-21",
      "sourceLanguage": "und",
      "license": "europepmc-oa",
      "specialty": "other",
      "harvestedAt": "2026-06-12T14:38:28.122Z",
      "licenseVerified": true,
      "sourceId": "europe_pmc_oa",
      "pmcid": "PMC13191780",
      "pmid": "42179472",
      "searchQuery": "(CASE REPORT) AND (OPEN_ACCESS:Y)",
      "isOpenAccess": true,
      "inPmc": true,
      "authorString": "Al Jaafar M, Aljafr ANS."
    },
    {
      "id": "75daa1cd-f678-4c78-91e6-b1126120736c",
      "doi": "10.1186/s12877-026-07281-5",
      "url": "https://europepmc.org/article/PMC/13069810",
      "title": "Flummoxed by the flaps - case report.",
      "journal": "BMC Geriatr",
      "publishedAt": "2026-03-05",
      "sourceLanguage": "und",
      "license": "europepmc-oa",
      "specialty": "other",
      "harvestedAt": "2026-06-12T14:38:28.122Z",
      "licenseVerified": true,
      "sourceId": "europe_pmc_oa",
      "pmcid": "PMC13069810",
      "pmid": "41782079",
      "searchQuery": "(CASE REPORT) AND (OPEN_ACCESS:Y)",
      "isOpenAccess": true,
      "inPmc": true,
      "authorString": "Pahwa B, Tasir PK, Sequeira RS, Khade M."
    },
    {
      "id": "e2c179cd-d011-43a8-8ce8-eaa6c96bb576",
      "url": "https://europepmc.org/article/PMC/13227292",
      "title": "Recurrent basosquamous carcinoma of the forearm, a case report",
      "journal": "JPRAS Open",
      "publishedAt": "2026-05-09",
      "sourceLanguage": "und",
      "license": "europepmc-oa",
      "specialty": "other",
      "harvestedAt": "2026-06-12T14:38:28.122Z",
      "licenseVerified": true,
      "sourceId": "europe_pmc_oa",
      "pmcid": "PMC13227292",
      "searchQuery": "(CASE REPORT) AND (OPEN_ACCESS:Y)",
      "isOpenAccess": true,
      "inPmc": true,
      "authorString": "Reiser D, Szallasi A, Sagerfors M."
    },
    {
      "id": "75218bfb-6ac7-40ac-bb59-2cbf48faa477",
      "doi": "10.1002/rcr2.70645",
      "url": "https://europepmc.org/article/PMC/13238797",
      "title": "Pulmonary Rheumatoid Nodules: A Case Report.",
      "journal": "Respirol Case Rep",
      "publishedAt": "2026-06-05",
      "sourceLanguage": "und",
      "license": "europepmc-oa",
      "specialty": "other",
      "harvestedAt": "2026-06-12T14:38:28.122Z",
      "licenseVerified": true,
      "sourceId": "europe_pmc_oa",
      "pmcid": "PMC13238797",
      "pmid": "42256661",
      "searchQuery": "(CASE REPORT) AND (OPEN_ACCESS:Y)",
      "isOpenAccess": true,
      "inPmc": true,
      "authorString": "Yuan M, Yin W, Wang L, Ye S."
    },
    {
      "id": "d7a7a5c7-410c-4412-a646-ce321cc83657",
      "doi": "10.1097/rc9.0000000000000413",
      "url": "https://europepmc.org/article/PMC/13166515",
      "title": "Adult megacystis-megaureter: a case report.",
      "journal": "Int J Surg Case Rep",
      "publishedAt": "2026-04-02",
      "sourceLanguage": "und",
      "license": "europepmc-oa",
      "specialty": "other",
      "harvestedAt": "2026-06-12T14:38:28.122Z",
      "licenseVerified": true,
      "sourceId": "europe_pmc_oa",
      "pmcid": "PMC13166515",
      "pmid": "42130564",
      "searchQuery": "(CASE REPORT) AND (OPEN_ACCESS:Y)",
      "isOpenAccess": true,
      "inPmc": true,
      "authorString": "Lamsal S, Karki G, Thapa S, Thapa BB."
    },
    {
      "id": "5de86cd3-b706-4232-ac89-11c3c77c1109",
      "doi": "10.1097/rc9.0000000000000499",
      "url": "https://europepmc.org/article/PMC/13236218",
      "title": "Supersize panniculectomy: a case report.",
      "journal": "Int J Surg Case Rep",
      "publishedAt": "2026-05-06",
      "sourceLanguage": "und",
      "license": "europepmc-oa",
      "specialty": "other",
      "harvestedAt": "2026-06-12T14:38:28.122Z",
      "licenseVerified": true,
      "sourceId": "europe_pmc_oa",
      "pmcid": "PMC13236218",
      "pmid": "42253666",
      "searchQuery": "(CASE REPORT) AND (OPEN_ACCESS:Y)",
      "isOpenAccess": true,
      "inPmc": true,
      "authorString": "Uderzo S, Boffo R, Lo Sapio B, Nicoletti MM, Borriello A, Faenza M."
    },
    {
      "id": "f10fd0f9-27d2-4cdd-b741-920ba1c2c7e6",
      "doi": "10.1093/ehjcr/ytag315",
      "url": "https://europepmc.org/article/PMC/13187633",
      "title": "Myopericarditis and leishmaniasis: a case report.",
      "journal": "Eur Heart J Case Rep",
      "publishedAt": "2026-05-05",
      "sourceLanguage": "und",
      "license": "europepmc-oa",
      "specialty": "other",
      "harvestedAt": "2026-06-12T14:38:28.122Z",
      "licenseVerified": true,
      "sourceId": "europe_pmc_oa",
      "pmcid": "PMC13187633",
      "pmid": "42170539",
      "searchQuery": "(CASE REPORT) AND (OPEN_ACCESS:Y)",
      "isOpenAccess": true,
      "inPmc": true,
      "authorString": "Cantos MB, Chango DX, Bravo J, Garcia-Zamora S, Baranchuk A."
    },
    {
      "id": "378377af-6dbf-45a8-9da0-5c9a639a3562",
      "url": "https://europepmc.org/article/PMC/13243312",
      "title": "Lichenoid drug eruption induced by letrozole: a case report",
      "journal": "Oxf Med Case Reports",
      "publishedAt": "2026-06-01",
      "sourceLanguage": "und",
      "license": "europepmc-oa",
      "specialty": "other",
      "harvestedAt": "2026-06-12T14:38:28.122Z",
      "licenseVerified": true,
      "sourceId": "europe_pmc_oa",
      "pmcid": "PMC13243312",
      "searchQuery": "(CASE REPORT) AND (OPEN_ACCESS:Y)",
      "isOpenAccess": true,
      "inPmc": true
    },
    {
      "id": "4dd035f7-1ba9-4ef6-a737-d73668473359",
      "url": "https://europepmc.org/article/PMC/13200264",
      "title": "Secretory carcinoma in the parotid gland: A case report",
      "journal": "Mol Clin Oncol",
      "publishedAt": "2026-05-07",
      "sourceLanguage": "und",
      "license": "europepmc-oa",
      "specialty": "other",
      "harvestedAt": "2026-06-12T14:38:28.122Z",
      "licenseVerified": true,
      "sourceId": "europe_pmc_oa",
      "pmcid": "PMC13200264",
      "searchQuery": "(CASE REPORT) AND (OPEN_ACCESS:Y)",
      "isOpenAccess": true,
      "inPmc": true,
      "authorString": "Hayashi M, Bandoh N, Goto T, Hayashi S, Arima R, Nakamuta K, Isochi-Yamaguchi T, Baba S, Kato Y, Takahara M, Takei H."
    },
    {
      "id": "92ee1238-a18f-400b-bd06-6a0c6861d80f",
      "doi": "10.1177/03000605261453484",
      "url": "https://europepmc.org/article/PMC/13237268",
      "title": "Primary tubercular chorioretinitis: A case report.",
      "journal": "J Int Med Res",
      "publishedAt": "2026-06-03",
      "sourceLanguage": "und",
      "license": "europepmc-oa",
      "specialty": "other",
      "harvestedAt": "2026-06-12T14:38:28.122Z",
      "licenseVerified": true,
      "sourceId": "europe_pmc_oa",
      "pmcid": "PMC13237268",
      "pmid": "42237072",
      "searchQuery": "(CASE REPORT) AND (OPEN_ACCESS:Y)",
      "isOpenAccess": true,
      "inPmc": true,
      "authorString": "Chen J."
    },
    {
      "id": "433666b4-bb17-4357-8fa0-06368d250f53",
      "url": "https://europepmc.org/article/PMC/13243311",
      "title": "Diagnosis and management of paediatric Nocardia keratitis: a case report",
      "journal": "Oxf Med Case Reports",
      "publishedAt": "2026-06-01",
      "sourceLanguage": "und",
      "license": "europepmc-oa",
      "specialty": "pediatrics",
      "harvestedAt": "2026-06-12T14:38:28.122Z",
      "licenseVerified": true,
      "sourceId": "europe_pmc_oa",
      "pmcid": "PMC13243311",
      "searchQuery": "(CASE REPORT) AND (OPEN_ACCESS:Y)",
      "isOpenAccess": true,
      "inPmc": true
    },
    {
      "id": "9af4b3b3-26b4-4a3d-8e0d-1be54cac9b0a",
      "doi": "10.1002/pcn5.70318",
      "url": "https://europepmc.org/article/PMC/13239329",
      "title": "Clozapine-induced diarrhea: A case report and mechanistic overview.",
      "journal": "PCN Rep",
      "publishedAt": "2026-05-28",
      "sourceLanguage": "und",
      "license": "europepmc-oa",
      "specialty": "other",
      "harvestedAt": "2026-06-12T14:38:28.122Z",
      "licenseVerified": true,
      "sourceId": "europe_pmc_oa",
      "pmcid": "PMC13239329",
      "pmid": "42256355",
      "searchQuery": "(CASE REPORT) AND (OPEN_ACCESS:Y)",
      "isOpenAccess": true,
      "inPmc": true,
      "authorString": "Dastmardi S, Namazi S."
    },
    {
      "id": "41f8d573-f499-453d-aee3-338b4b3681f2",
      "doi": "10.1002/ccr3.72739",
      "url": "https://europepmc.org/article/PMC/13238692",
      "title": "Solitary Neurofibroma of the Hypopharynx: A Case Report.",
      "journal": "Clin Case Rep",
      "publishedAt": "2026-05-22",
      "sourceLanguage": "und",
      "license": "europepmc-oa",
      "specialty": "other",
      "harvestedAt": "2026-06-12T14:38:28.122Z",
      "licenseVerified": true,
      "sourceId": "europe_pmc_oa",
      "pmcid": "PMC13238692",
      "pmid": "42256935",
      "searchQuery": "(CASE REPORT) AND (OPEN_ACCESS:Y)",
      "isOpenAccess": true,
      "inPmc": true,
      "authorString": "Ghazizadeh M, Amooeian VG."
    },
    {
      "id": "8861597f-9ecd-493e-9c88-9f5904bc5df1",
      "doi": "10.25259/sni_219_2026",
      "url": "https://europepmc.org/article/PMC/13224257",
      "title": "OS odontoideum in an achondroplastic adult - A case report and review.",
      "journal": "Surg Neurol Int",
      "publishedAt": "2026-05-22",
      "sourceLanguage": "und",
      "license": "europepmc-oa",
      "specialty": "other",
      "harvestedAt": "2026-06-12T14:38:28.122Z",
      "licenseVerified": true,
      "sourceId": "europe_pmc_oa",
      "pmcid": "PMC13224257",
      "pmid": "42232456",
      "searchQuery": "(CASE REPORT) AND (OPEN_ACCESS:Y)",
      "isOpenAccess": true,
      "inPmc": true,
      "authorString": "Mollahouseini R, Rahimizadeh A, Wiliamson W."
    },
    {
      "id": "ce825b55-6939-4e26-9216-23ecabe37368",
      "doi": "10.1177/2050313x261446097",
      "url": "https://europepmc.org/article/PMC/13191113",
      "title": "Sucking pads in infancy: A physiologic finding - A case report.",
      "journal": "SAGE Open Med Case Rep",
      "publishedAt": "2026-05-20",
      "sourceLanguage": "und",
      "license": "europepmc-oa",
      "specialty": "other",
      "harvestedAt": "2026-06-12T14:38:28.122Z",
      "licenseVerified": true,
      "sourceId": "europe_pmc_oa",
      "pmcid": "PMC13191113",
      "pmid": "42180619",
      "searchQuery": "(CASE REPORT) AND (OPEN_ACCESS:Y)",
      "isOpenAccess": true,
      "inPmc": true,
      "authorString": "Pynn E, Hamm C, Beecker J."
    },
    {
      "id": "877a22d8-03cd-4a79-80eb-e8a662240b46",
      "doi": "10.7759/cureus.107659",
      "url": "https://europepmc.org/article/PMC/13198889",
      "title": "A Case Report of Bouveret Syndrome.",
      "journal": "Cureus",
      "publishedAt": "2026-04-24",
      "sourceLanguage": "und",
      "license": "europepmc-oa",
      "specialty": "other",
      "harvestedAt": "2026-06-12T14:38:28.122Z",
      "licenseVerified": true,
      "sourceId": "europe_pmc_oa",
      "pmcid": "PMC13198889",
      "pmid": "42186657",
      "searchQuery": "(CASE REPORT) AND (OPEN_ACCESS:Y)",
      "isOpenAccess": true,
      "inPmc": true,
      "authorString": "Rentería Fonseca QM, Fragoza Aguillares EO, Sanchez Bravo JA, Maza Gomez R."
    },
    {
      "id": "5c2034ce-fee9-46d1-bd0d-b4ad8a07c6f9",
      "url": "https://europepmc.org/article/PMC/13244037",
      "title": "Pericardial Hemangioma : A Case Report and Updated Literature Review",
      "journal": "JACC Case Rep",
      "publishedAt": "2026-06-03",
      "sourceLanguage": "und",
      "license": "europepmc-oa",
      "specialty": "other",
      "harvestedAt": "2026-06-12T14:38:28.122Z",
      "licenseVerified": true,
      "sourceId": "europe_pmc_oa",
      "pmcid": "PMC13244037",
      "searchQuery": "(CASE REPORT) AND (OPEN_ACCESS:Y)",
      "isOpenAccess": true,
      "inPmc": true,
      "authorString": "Azees R, Udongwo N, Esomonye T, Kalle F, Amin S, Echols M."
    },
    {
      "id": "106badb5-660c-4239-9cfe-be5e6ed470e4",
      "doi": "10.3389/fmed.2026.1765443",
      "url": "https://europepmc.org/article/PMC/13237683",
      "title": "Micronodular PEComa of the appendix: a case report.",
      "journal": "Front Med (Lausanne)",
      "publishedAt": "2026-05-22",
      "sourceLanguage": "und",
      "license": "europepmc-oa",
      "specialty": "other",
      "harvestedAt": "2026-06-12T14:38:28.122Z",
      "licenseVerified": true,
      "sourceId": "europe_pmc_oa",
      "pmcid": "PMC13237683",
      "pmid": "42254402",
      "searchQuery": "(CASE REPORT) AND (OPEN_ACCESS:Y)",
      "isOpenAccess": true,
      "inPmc": true,
      "authorString": "Jiang LJ, Wang CQ, Xu ZG."
    },
    {
      "id": "de95268b-5875-453a-9c0e-64fbd367f81d",
      "doi": "10.7759/cureus.103473",
      "url": "https://europepmc.org/article/PMC/12989118",
      "title": "Carrington's Disease: A Case Report.",
      "journal": "Cureus",
      "publishedAt": "2026-02-12",
      "sourceLanguage": "und",
      "license": "europepmc-oa",
      "specialty": "other",
      "harvestedAt": "2026-06-12T14:38:28.122Z",
      "licenseVerified": true,
      "sourceId": "europe_pmc_oa",
      "pmcid": "PMC12989118",
      "pmid": "41841088",
      "searchQuery": "(CASE REPORT) AND (OPEN_ACCESS:Y)",
      "isOpenAccess": true,
      "inPmc": true,
      "authorString": "Bouali S, Gartini S, Rhazari M, Thouil A, Kouismi H."
    },
    {
      "id": "f96af4ad-0df1-4326-b993-082a1b5bc9e3",
      "doi": "10.1002/ccr3.72757",
      "url": "https://europepmc.org/article/PMC/13239148",
      "title": "Maxillofacial Cemento-Ossifying Fibroma: A Rare Case Report.",
      "journal": "Clin Case Rep",
      "publishedAt": "2026-05-22",
      "sourceLanguage": "und",
      "license": "europepmc-oa",
      "specialty": "other",
      "harvestedAt": "2026-06-12T14:38:28.122Z",
      "licenseVerified": true,
      "sourceId": "europe_pmc_oa",
      "pmcid": "PMC13239148",
      "pmid": "42256946",
      "searchQuery": "(CASE REPORT) AND (OPEN_ACCESS:Y)",
      "isOpenAccess": true,
      "inPmc": true,
      "authorString": "Kamina AN, Mbombo EN, Badibanga P, Tague C, Lutumba P, Koba Mjumbe C."
    },
    {
      "id": "5995850a-622e-4ee8-b92b-25506bbc89b4",
      "doi": "10.25259/sni_1454_2025",
      "url": "https://europepmc.org/article/PMC/13157934",
      "title": "Infratentorial neuroparacoccidioidomycosis: A case report.",
      "journal": "Surg Neurol Int",
      "publishedAt": "2026-04-17",
      "sourceLanguage": "und",
      "license": "europepmc-oa",
      "specialty": "other",
      "harvestedAt": "2026-06-12T14:38:28.122Z",
      "licenseVerified": true,
      "sourceId": "europe_pmc_oa",
      "pmcid": "PMC13157934",
      "pmid": "42116905",
      "searchQuery": "(CASE REPORT) AND (OPEN_ACCESS:Y)",
      "isOpenAccess": true,
      "inPmc": true,
      "authorString": "Della Bona DS, Dos Santos Júnior RA, Mesquita Filho PM, Penno AE, Mesa Casa EB, Franz APG, Schwingel D, Padua WL."
    },
    {
      "id": "18fda7c4-3d86-41a8-8765-6bee33c56410",
      "url": "https://europepmc.org/article/PMC/13093467",
      "title": "Management of Cushing’s Disease in Pregnancy: A Case Report",
      "journal": "Cureus",
      "publishedAt": "2026-04-22",
      "sourceLanguage": "und",
      "license": "europepmc-oa",
      "specialty": "other",
      "harvestedAt": "2026-06-12T14:38:28.122Z",
      "licenseVerified": true,
      "sourceId": "europe_pmc_oa",
      "pmcid": "PMC13093467",
      "searchQuery": "(CASE REPORT) AND (OPEN_ACCESS:Y)",
      "isOpenAccess": true,
      "inPmc": true,
      "authorString": "Mukherjee G, Manmathan S, Zachariah S, Arokisamy J, Kar S."
    },
    {
      "id": "90050493-81a8-434a-8122-ec2b325e7a65",
      "url": "https://europepmc.org/article/PMC/13095189",
      "title": "Syphilitic Tonsillitis: A Case Report and Review of the Literature",
      "journal": "Cureus",
      "publishedAt": "2026-04-22",
      "sourceLanguage": "und",
      "license": "europepmc-oa",
      "specialty": "other",
      "harvestedAt": "2026-06-12T14:38:28.122Z",
      "licenseVerified": true,
      "sourceId": "europe_pmc_oa",
      "pmcid": "PMC13095189",
      "searchQuery": "(CASE REPORT) AND (OPEN_ACCESS:Y)",
      "isOpenAccess": true,
      "inPmc": true,
      "authorString": "Ganaiem A, Grigoraki A, Spanou K, Kanna E, Potamianos S."
    },
    {
      "id": "b71a2530-1ac2-4627-ae38-6c12f4da74d8",
      "doi": "10.1093/ehjcr/ytag191",
      "url": "https://europepmc.org/article/PMC/13012604",
      "title": "Exercise stress cardiomyopathy-a case report.",
      "journal": "Eur Heart J Case Rep",
      "publishedAt": "2026-03-12",
      "sourceLanguage": "und",
      "license": "europepmc-oa",
      "specialty": "other",
      "harvestedAt": "2026-06-12T14:38:28.122Z",
      "licenseVerified": true,
      "sourceId": "europe_pmc_oa",
      "pmcid": "PMC13012604",
      "pmid": "41883603",
      "searchQuery": "(CASE REPORT) AND (OPEN_ACCESS:Y)",
      "isOpenAccess": true,
      "inPmc": true,
      "authorString": "Russell PL, Martin J, Dwan MJ, Holland DJ."
    },
    {
      "id": "8b1c6863-c755-4d64-bf57-c1470ae22943",
      "doi": "10.1155/cro/6636850",
      "url": "https://europepmc.org/article/PMC/13181422",
      "title": "Congenital Anomalies of the Knee-Hypoplasia of the Meniscus: A Case Report.",
      "journal": "Case Rep Orthop",
      "publishedAt": "2026-05-18",
      "sourceLanguage": "und",
      "license": "europepmc-oa",
      "specialty": "other",
      "harvestedAt": "2026-06-12T14:38:28.122Z",
      "licenseVerified": true,
      "sourceId": "europe_pmc_oa",
      "pmcid": "PMC13181422",
      "pmid": "42158592",
      "searchQuery": "(CASE REPORT) AND (OPEN_ACCESS:Y)",
      "isOpenAccess": true,
      "inPmc": true,
      "authorString": "Paa A, Ford D, Woodhams W, Galardi W, Mbengue A, Lissy M."
    },
    {
      "id": "b2c5e764-5714-4fbf-9657-deb1837c313d",
      "doi": "10.1155/crie/9876731",
      "url": "https://europepmc.org/article/PMC/13240417",
      "title": "Correction to \"A Decade With Sheehan's Syndrome: A Case Report and Personal Experience\".",
      "journal": "Case Rep Endocrinol",
      "publishedAt": "2026-06-03",
      "sourceLanguage": "und",
      "license": "europepmc-oa",
      "specialty": "other",
      "harvestedAt": "2026-06-12T14:38:28.122Z",
      "licenseVerified": true,
      "sourceId": "europe_pmc_oa",
      "pmcid": "PMC13240417",
      "pmid": "42256319",
      "searchQuery": "(CASE REPORT) AND (OPEN_ACCESS:Y)",
      "isOpenAccess": true,
      "inPmc": true
    },
    {
      "id": "4f829d32-7d6e-472b-846a-d0647475bfcd",
      "doi": "10.1155/carm/8323943",
      "url": "https://europepmc.org/article/PMC/13095480",
      "title": "Pulmonary Thromboembolism in a Patient With Behçet's Disease: A Case Report.",
      "journal": "Case Rep Med",
      "publishedAt": "2026-04-20",
      "sourceLanguage": "und",
      "license": "europepmc-oa",
      "specialty": "other",
      "harvestedAt": "2026-06-12T14:38:28.122Z",
      "licenseVerified": true,
      "sourceId": "europe_pmc_oa",
      "pmcid": "PMC13095480",
      "pmid": "42023413",
      "searchQuery": "(CASE REPORT) AND (OPEN_ACCESS:Y)",
      "isOpenAccess": true,
      "inPmc": true,
      "authorString": "Kalantari E, Emami Ardestani M."
    },
    {
      "id": "bb65de13-5ed1-44a7-8226-11de7a195f7d",
      "doi": "10.1093/jscr/rjag234",
      "url": "https://europepmc.org/article/PMC/13070703",
      "title": "Appendiceal duplication with Amyand's hernia: a case report.",
      "journal": "J Surg Case Rep",
      "publishedAt": "2026-04-11",
      "sourceLanguage": "und",
      "license": "europepmc-oa",
      "specialty": "other",
      "harvestedAt": "2026-06-12T14:38:28.122Z",
      "licenseVerified": true,
      "sourceId": "europe_pmc_oa",
      "pmcid": "PMC13070703",
      "pmid": "41978808",
      "searchQuery": "(CASE REPORT) AND (OPEN_ACCESS:Y)",
      "isOpenAccess": true,
      "inPmc": true,
      "authorString": "Ripe DC, Cuellar JS, Buitrago Lozano G, Alfonso MM."
    },
    {
      "id": "c76f9cc8-bea5-405a-ada5-32112b4e037a",
      "url": "https://europepmc.org/article/PMC/13249417",
      "title": "Unilateral Panuveitis Secondary to Toxoplasmosis in an Immunocompromised Patient: A Case Report",
      "journal": "Cureus",
      "publishedAt": "2026-06-10",
      "sourceLanguage": "und",
      "license": "europepmc-oa",
      "specialty": "other",
      "harvestedAt": "2026-06-12T14:38:28.122Z",
      "licenseVerified": true,
      "sourceId": "europe_pmc_oa",
      "pmcid": "PMC13249417",
      "searchQuery": "(CASE REPORT) AND (OPEN_ACCESS:Y)",
      "isOpenAccess": true,
      "inPmc": true,
      "authorString": "Rahman N, Narayan A, Groppe M, Bindra M, Kalogeropoulos D."
    },
    {
      "id": "e12f2fc1-9b56-46bc-b7b5-50afd6587501",
      "doi": "10.3389/fmed.2026.1791234",
      "url": "https://europepmc.org/article/PMC/13099282",
      "title": "Case Report: A case of Fournier's gangrene of the scrotum.",
      "journal": "Front Med (Lausanne)",
      "publishedAt": "2026-04-08",
      "sourceLanguage": "und",
      "license": "europepmc-oa",
      "specialty": "other",
      "harvestedAt": "2026-06-12T14:38:28.122Z",
      "licenseVerified": true,
      "sourceId": "europe_pmc_oa",
      "pmcid": "PMC13099282",
      "pmid": "42027829",
      "searchQuery": "(CASE REPORT) AND (OPEN_ACCESS:Y)",
      "isOpenAccess": true,
      "inPmc": true,
      "authorString": "Yuan L, Sun Y, Yan J."
    },
    {
      "id": "e78c9f55-16ac-4da5-8423-f83f25287b97",
      "doi": "10.3389/fsurg.2026.1807545",
      "url": "https://europepmc.org/article/PMC/13194519",
      "title": "Suprainguinal ectopic scrotum: a case report.",
      "journal": "Front Surg",
      "publishedAt": "2026-05-08",
      "sourceLanguage": "und",
      "license": "europepmc-oa",
      "specialty": "other",
      "harvestedAt": "2026-06-12T14:38:28.122Z",
      "licenseVerified": true,
      "sourceId": "europe_pmc_oa",
      "pmcid": "PMC13194519",
      "pmid": "42181542",
      "searchQuery": "(CASE REPORT) AND (OPEN_ACCESS:Y)",
      "isOpenAccess": true,
      "inPmc": true,
      "authorString": "Chen X, Pan W, Qian W, Xia L."
    },
    {
      "id": "a39a6e6a-58a0-4575-8cc6-ed40ff11667e",
      "doi": "10.1002/ccr3.72473",
      "url": "https://europepmc.org/article/PMC/13052132",
      "title": "Dupilumab for Trichothiodystrophy-Case Report and Review of the Literature.",
      "journal": "Clin Case Rep",
      "publishedAt": "2026-04-03",
      "sourceLanguage": "und",
      "license": "europepmc-oa",
      "specialty": "other",
      "harvestedAt": "2026-06-12T14:38:28.122Z",
      "licenseVerified": true,
      "sourceId": "europe_pmc_oa",
      "pmcid": "PMC13052132",
      "pmid": "41948753",
      "searchQuery": "(CASE REPORT) AND (OPEN_ACCESS:Y)",
      "isOpenAccess": true,
      "inPmc": true,
      "authorString": "O'Mahony J, O'Connor C."
    },
    {
      "id": "8996e4c2-9420-4e7f-9e19-68a952b689a8",
      "url": "https://europepmc.org/article/PMC/13248557",
      "title": "Humeroradioulnar Synostosis in a Patient with Underlying Congenital Scoliosis: A Case Report",
      "journal": "J Orthop Case Rep",
      "publishedAt": "2026-06-01",
      "sourceLanguage": "und",
      "license": "europepmc-oa",
      "specialty": "other",
      "harvestedAt": "2026-06-12T14:38:28.122Z",
      "licenseVerified": true,
      "sourceId": "europe_pmc_oa",
      "pmcid": "PMC13248557",
      "searchQuery": "(CASE REPORT) AND (OPEN_ACCESS:Y)",
      "isOpenAccess": true,
      "inPmc": true,
      "authorString": "Small T, Kahwaty S, Stall A."
    },
    {
      "id": "756d988b-793d-44df-90fd-82c8b3a1afb8",
      "doi": "10.3389/fopht.2026.1806872",
      "url": "https://europepmc.org/article/PMC/13189758",
      "title": "Poroid hidradenoma of the eyelid: a case report.",
      "journal": "Front Ophthalmol (Lausanne)",
      "publishedAt": "2026-05-07",
      "sourceLanguage": "und",
      "license": "europepmc-oa",
      "specialty": "other",
      "harvestedAt": "2026-06-12T14:38:28.122Z",
      "licenseVerified": true,
      "sourceId": "europe_pmc_oa",
      "pmcid": "PMC13189758",
      "pmid": "42183084",
      "searchQuery": "(CASE REPORT) AND (OPEN_ACCESS:Y)",
      "isOpenAccess": true,
      "inPmc": true,
      "authorString": "Nieves-Rios C, López-Fontanet JJ, Serrano-Olmo J, Campbell J."
    },
    {
      "id": "84b39520-87e1-4f5e-a00a-f2d510aeb872",
      "url": "https://europepmc.org/article/PMC/13225949",
      "title": "A rare case of primary bladder malignant melanoma: a case report",
      "journal": "Front Oncol",
      "publishedAt": "2026-06-04",
      "sourceLanguage": "und",
      "license": "europepmc-oa",
      "specialty": "other",
      "harvestedAt": "2026-06-12T14:38:28.122Z",
      "licenseVerified": true,
      "sourceId": "europe_pmc_oa",
      "pmcid": "PMC13225949",
      "searchQuery": "(CASE REPORT) AND (OPEN_ACCESS:Y)",
      "isOpenAccess": true,
      "inPmc": true,
      "authorString": "Yu Y, Nie X."
    },
    {
      "id": "3379b216-b507-43cd-91f4-b571a059dbff",
      "url": "https://europepmc.org/article/PMC/13243316",
      "title": "Adenoid cystic carcinoma of the breast: a case report and literature review",
      "journal": "Oxf Med Case Reports",
      "publishedAt": "2026-06-01",
      "sourceLanguage": "und",
      "license": "europepmc-oa",
      "specialty": "other",
      "harvestedAt": "2026-06-12T14:38:28.122Z",
      "licenseVerified": true,
      "sourceId": "europe_pmc_oa",
      "pmcid": "PMC13243316",
      "searchQuery": "(CASE REPORT) AND (OPEN_ACCESS:Y)",
      "isOpenAccess": true,
      "inPmc": true
    },
    {
      "id": "a36445ea-48fd-4893-80e7-61c08698849d",
      "url": "https://europepmc.org/article/PMC/13248052",
      "title": "Paroxysmal supraventricular tachycardia associated with dexmedetomidine withdrawal in an adult liver transplant recipient: A case report",
      "journal": "World J Crit Care Med",
      "publishedAt": "2026-06-09",
      "sourceLanguage": "und",
      "license": "europepmc-oa",
      "specialty": "internal_medicine",
      "harvestedAt": "2026-06-12T14:38:28.122Z",
      "licenseVerified": true,
      "sourceId": "europe_pmc_oa",
      "pmcid": "PMC13248052",
      "searchQuery": "(intensive care OR critical care) AND (case report) AND (OPEN_ACCESS:Y)",
      "isOpenAccess": true,
      "inPmc": true
    },
    {
      "id": "78b7d392-081d-435f-9758-9f613361bdef",
      "doi": "10.1097/ea9.0000000000000115",
      "url": "https://europepmc.org/article/PMC/13232903",
      "title": "An unusual case of burst suppression electrographic pattern following intrathecal baclofen overdose in critical care: a case report.",
      "journal": "Eur J Anaesthesiol Intensive Care",
      "publishedAt": "2026-05-18",
      "sourceLanguage": "und",
      "license": "europepmc-oa",
      "specialty": "critical_care",
      "harvestedAt": "2026-06-12T14:38:28.122Z",
      "licenseVerified": true,
      "sourceId": "europe_pmc_oa",
      "pmcid": "PMC13232903",
      "pmid": "42244827",
      "searchQuery": "(intensive care OR critical care) AND (case report) AND (OPEN_ACCESS:Y)",
      "isOpenAccess": true,
      "inPmc": true,
      "authorString": "Elhadjene N, Soulier H."
    },
    {
      "id": "1a3d5287-5c3c-4fba-b595-7678ada0f4ce",
      "doi": "10.14309/crj.0000000000002085",
      "url": "https://europepmc.org/article/PMC/13197023",
      "title": "Severe Acute Pancreatitis Complicated by Guillain-Barré Syndrome in the Intensive Care Unit.",
      "journal": "ACG Case Rep J",
      "publishedAt": "2026-05-22",
      "sourceLanguage": "und",
      "license": "europepmc-oa",
      "specialty": "critical_care",
      "harvestedAt": "2026-06-12T14:38:28.122Z",
      "licenseVerified": true,
      "sourceId": "europe_pmc_oa",
      "pmcid": "PMC13197023",
      "pmid": "42182590",
      "searchQuery": "(intensive care OR critical care) AND (case report) AND (OPEN_ACCESS:Y)",
      "isOpenAccess": true,
      "inPmc": true,
      "authorString": "Wang D, Meng X, Ye T, Zhu C."
    },
    {
      "id": "73a6b2f9-75fe-474c-bf9e-739373685e82",
      "doi": "10.2147/imcrj.s608541",
      "url": "https://europepmc.org/article/PMC/13217447",
      "title": "Severe Post-Measles ARDS with Multisystem Complications in an Unvaccinated Child in a Resource-Limited Setting: A Case Report.",
      "journal": "Int Med Case Rep J",
      "publishedAt": "2026-05-23",
      "sourceLanguage": "und",
      "license": "europepmc-oa",
      "specialty": "critical_care",
      "harvestedAt": "2026-06-12T14:38:28.122Z",
      "licenseVerified": true,
      "sourceId": "europe_pmc_oa",
      "pmcid": "PMC13217447",
      "pmid": "42220620",
      "searchQuery": "(intensive care OR critical care) AND (case report) AND (OPEN_ACCESS:Y)",
      "isOpenAccess": true,
      "inPmc": true,
      "authorString": "Siyad AO, Hassan AM, Hassan RA."
    },
    {
      "id": "f375b1c3-8103-45d6-89ee-58cea6bf9cf8",
      "doi": "10.7759/cureus.108467",
      "url": "https://europepmc.org/article/PMC/13242618",
      "title": "A Fatal Case of Fulminant Panton-Valentine Leukocidin-Positive Methicillin-Resistant Staphylococcus aureus Necrotising Pneumonia in a Previously Healthy Adolescent: A Case Report.",
      "journal": "Cureus",
      "publishedAt": "2026-05-08",
      "sourceLanguage": "und",
      "license": "europepmc-oa",
      "specialty": "pediatrics",
      "harvestedAt": "2026-06-12T14:38:28.122Z",
      "licenseVerified": true,
      "sourceId": "europe_pmc_oa",
      "pmcid": "PMC13242618",
      "pmid": "42261547",
      "searchQuery": "(intensive care OR critical care) AND (case report) AND (OPEN_ACCESS:Y)",
      "isOpenAccess": true,
      "inPmc": true,
      "authorString": "Hogsade Z, Raggett A, Dosu A, De Silva-Morgan M."
    },
    {
      "id": "0e016664-4c28-40dd-bee2-70e40368bd51",
      "doi": "10.7759/cureus.107636",
      "url": "https://europepmc.org/article/PMC/13110120",
      "title": "Exploring the Characteristics and Outcomes of Centenarian Patients Admitted to Intensive Care Units: A Systematised Narrative Review.",
      "journal": "Cureus",
      "publishedAt": "2026-04-24",
      "sourceLanguage": "und",
      "license": "europepmc-oa",
      "specialty": "critical_care",
      "harvestedAt": "2026-06-12T14:38:28.122Z",
      "licenseVerified": true,
      "sourceId": "europe_pmc_oa",
      "pmcid": "PMC13110120",
      "pmid": "42038739",
      "searchQuery": "(intensive care OR critical care) AND (case report) AND (OPEN_ACCESS:Y)",
      "isOpenAccess": true,
      "inPmc": true,
      "authorString": "Reyneke C, Raykateeraroj N, Suh J, Zand J, Lee DK, Weinberg L."
    },
    {
      "id": "a1b639e7-6443-4e7b-abcc-2448972218f2",
      "doi": "10.1111/nicc.70513",
      "url": "https://europepmc.org/article/PMC/13173495",
      "title": "The Effects of Nursing Care Applied in the Intensive Care Unit on a Case of Toxic Epidermal Necrolysis: A Case Report.",
      "journal": "Nurs Crit Care",
      "publishedAt": "2026-05-01",
      "sourceLanguage": "und",
      "license": "europepmc-oa",
      "specialty": "critical_care",
      "harvestedAt": "2026-06-12T14:38:28.122Z",
      "licenseVerified": true,
      "sourceId": "europe_pmc_oa",
      "pmcid": "PMC13173495",
      "pmid": "42132071",
      "searchQuery": "(intensive care OR critical care) AND (case report) AND (OPEN_ACCESS:Y)",
      "isOpenAccess": true,
      "inPmc": true,
      "authorString": "Gulsoy Z, Özdemir Kol İ."
    },
    {
      "id": "6100922a-68cc-41aa-b232-8a3db0c94b17",
      "doi": "10.1155/crcc/1700879",
      "url": "https://europepmc.org/article/PMC/13162226",
      "title": "High-Dependency Care Without Mechanical Ventilation for Severe Guillain-Barré Syndrome in a Rural Low-Income Setting.",
      "journal": "Case Rep Crit Care",
      "publishedAt": "2026-05-12",
      "sourceLanguage": "und",
      "license": "europepmc-oa",
      "specialty": "critical_care",
      "harvestedAt": "2026-06-12T14:38:28.122Z",
      "licenseVerified": true,
      "sourceId": "europe_pmc_oa",
      "pmcid": "PMC13162226",
      "pmid": "42131123",
      "searchQuery": "(intensive care OR critical care) AND (case report) AND (OPEN_ACCESS:Y)",
      "isOpenAccess": true,
      "inPmc": true,
      "authorString": "Notghi L, Little L, Chin J."
    },
    {
      "id": "66a52117-4bcf-4b62-b08c-b5df1ea4fc13",
      "doi": "10.1038/s41598-026-54854-w",
      "url": "https://europepmc.org/article/PMC/13201853",
      "title": "Impact of a structured case report on self-reported responses to simulated emergency scenarios: a randomized survey-based study.",
      "journal": "Sci Rep",
      "publishedAt": "2026-05-25",
      "sourceLanguage": "und",
      "license": "europepmc-oa",
      "specialty": "critical_care",
      "harvestedAt": "2026-06-12T14:38:28.122Z",
      "licenseVerified": true,
      "sourceId": "europe_pmc_oa",
      "pmcid": "PMC13201853",
      "pmid": "42185433",
      "searchQuery": "(intensive care OR critical care) AND (case report) AND (OPEN_ACCESS:Y)",
      "isOpenAccess": true,
      "inPmc": true,
      "authorString": "Porschen C, Hellenthal KEM, Zarbock A, Fujarski M, Brauckmann P, Nguyen TN, Rehberg S, Wnent J, Lange M."
    },
    {
      "id": "9867b05e-230c-4099-9406-7f5255255430",
      "doi": "10.1177/11795476261444444",
      "url": "https://europepmc.org/article/PMC/13110295",
      "title": "Post-streptococcal Glomerulonephritis Presenting With Acute Pulmonary Edema and Critical Hyperkalemia: A Rare Pediatric Case Report From Yemen.",
      "journal": "Clin Med Insights Case Rep",
      "publishedAt": "2026-04-20",
      "sourceLanguage": "und",
      "license": "europepmc-oa",
      "specialty": "pediatrics",
      "harvestedAt": "2026-06-12T14:38:28.122Z",
      "licenseVerified": true,
      "sourceId": "europe_pmc_oa",
      "pmcid": "PMC13110295",
      "pmid": "42046828",
      "searchQuery": "(intensive care OR critical care) AND (case report) AND (OPEN_ACCESS:Y)",
      "isOpenAccess": true,
      "inPmc": true,
      "authorString": "Mohamed AAA, Ayish MKM, Muafa HM."
    },
    {
      "id": "f3128faa-a216-4098-b544-31fbb4aac226",
      "doi": "10.7759/cureus.109077",
      "url": "https://europepmc.org/article/PMC/13181500",
      "title": "Artery of Percheron Syndrome From a Possible Paradoxical Embolus in the Intensive Care Unit: An Easily Missed Diagnosis in Intubated Patients.",
      "journal": "Cureus",
      "publishedAt": "2026-05-18",
      "sourceLanguage": "und",
      "license": "europepmc-oa",
      "specialty": "critical_care",
      "harvestedAt": "2026-06-12T14:38:28.122Z",
      "licenseVerified": true,
      "sourceId": "europe_pmc_oa",
      "pmcid": "PMC13181500",
      "pmid": "42158407",
      "searchQuery": "(intensive care OR critical care) AND (case report) AND (OPEN_ACCESS:Y)",
      "isOpenAccess": true,
      "inPmc": true,
      "authorString": "Nirmalan V."
    },
    {
      "id": "17849676-8561-4fbf-b720-fca643e45764",
      "doi": "10.1155/crcc/2549155",
      "url": "https://europepmc.org/article/PMC/13189493",
      "title": "Management of an Autism Spectrum Disorder (ASD) Patient With Respiratory Failure in the Intensive Care Unit: A Case Report on the Role of Dexmedetomidine.",
      "journal": "Case Rep Crit Care",
      "publishedAt": "2026-05-20",
      "sourceLanguage": "und",
      "license": "europepmc-oa",
      "specialty": "critical_care",
      "harvestedAt": "2026-06-12T14:38:28.122Z",
      "licenseVerified": true,
      "sourceId": "europe_pmc_oa",
      "pmcid": "PMC13189493",
      "pmid": "42169815",
      "searchQuery": "(intensive care OR critical care) AND (case report) AND (OPEN_ACCESS:Y)",
      "isOpenAccess": true,
      "inPmc": true,
      "authorString": "Ciccozzi A, Murgia F, Piroli A, Paladini A, Ciccone C, Leonardis F, Fionda D, Ciccone A, Marinangeli F."
    },
    {
      "id": "df8cb2b5-b811-4715-aa9e-7e64dc71e61c",
      "url": "https://europepmc.org/article/PMC/13246663",
      "title": "Case Report: Early management and successful thrombolysis in two cases of high-risk pulmonary embolism",
      "journal": "Front Med (Lausanne)",
      "publishedAt": "2026-06-10",
      "sourceLanguage": "und",
      "license": "europepmc-oa",
      "specialty": "critical_care",
      "harvestedAt": "2026-06-12T14:38:28.122Z",
      "licenseVerified": true,
      "sourceId": "europe_pmc_oa",
      "pmcid": "PMC13246663",
      "searchQuery": "(intensive care OR critical care) AND (case report) AND (OPEN_ACCESS:Y)",
      "isOpenAccess": true,
      "inPmc": true,
      "authorString": "Zhang Y, Li J, Deng Y, Meng J, Zhou W, Luo F, Deng W."
    },
    {
      "id": "f2c8de04-7c75-4c1b-a043-5fb704719a23",
      "url": "https://europepmc.org/article/PMC/13249000",
      "title": "Fundamental Principles of Bioethics and Their Implementation in the Paediatric Intensive Care Unit: Clinical Complexities and the Imperative for Structured Ethics Education",
      "journal": "Cureus",
      "publishedAt": "2026-06-10",
      "sourceLanguage": "und",
      "license": "europepmc-oa",
      "specialty": "critical_care",
      "harvestedAt": "2026-06-12T14:38:28.122Z",
      "licenseVerified": true,
      "sourceId": "europe_pmc_oa",
      "pmcid": "PMC13249000",
      "searchQuery": "(intensive care OR critical care) AND (case report) AND (OPEN_ACCESS:Y)",
      "isOpenAccess": true,
      "inPmc": true,
      "authorString": "Straka K, Christakou E."
    },
    {
      "id": "1e785926-3407-4cf5-9fa2-74f0e56aa05a",
      "doi": "10.1002/rcr2.70636",
      "url": "https://europepmc.org/article/PMC/13239305",
      "title": "Post-Transfusion Purpura: A Clinical Case With Alveolar Haemorrhage.",
      "journal": "Respirol Case Rep",
      "publishedAt": "2026-06-02",
      "sourceLanguage": "und",
      "license": "europepmc-oa",
      "specialty": "critical_care",
      "harvestedAt": "2026-06-12T14:38:28.122Z",
      "licenseVerified": true,
      "sourceId": "europe_pmc_oa",
      "pmcid": "PMC13239305",
      "pmid": "42256651",
      "searchQuery": "(intensive care OR critical care) AND (case report) AND (OPEN_ACCESS:Y)",
      "isOpenAccess": true,
      "inPmc": true,
      "authorString": "Yamakova Y, Pisanchev A, Farfarov A, Petkov R."
    },
    {
      "id": "fb1d54a1-8c99-485a-8adb-c493328ee29b",
      "doi": "10.1016/j.toxrep.2026.102275",
      "url": "https://europepmc.org/article/PMC/13208102",
      "title": "Survival after severe aluminum phosphide poisoning complicated by concurrent insulin overdose: A case report.",
      "journal": "Toxicol Rep",
      "publishedAt": "2026-05-15",
      "sourceLanguage": "und",
      "license": "europepmc-oa",
      "specialty": "critical_care",
      "harvestedAt": "2026-06-12T14:38:28.122Z",
      "licenseVerified": true,
      "sourceId": "europe_pmc_oa",
      "pmcid": "PMC13208102",
      "pmid": "42205532",
      "searchQuery": "(intensive care OR critical care) AND (case report) AND (OPEN_ACCESS:Y)",
      "isOpenAccess": true,
      "inPmc": true,
      "authorString": "Rasouli M, Goli R, Mohammadi N, Karimi N."
    },
    {
      "id": "4794c675-c536-46b7-9415-62b9e3b1a317",
      "doi": "10.1136/bmjopen-2026-117840",
      "url": "https://europepmc.org/article/PMC/13202168",
      "title": "Understanding how post-intensive care follow-up is delivered within the role of critical care outreach teams: a qualitative study protocol.",
      "journal": "BMJ Open",
      "publishedAt": "2026-05-24",
      "sourceLanguage": "und",
      "license": "europepmc-oa",
      "specialty": "critical_care",
      "harvestedAt": "2026-06-12T14:38:28.122Z",
      "licenseVerified": true,
      "sourceId": "europe_pmc_oa",
      "pmcid": "PMC13202168",
      "pmid": "42192619",
      "searchQuery": "(intensive care OR critical care) AND (case report) AND (OPEN_ACCESS:Y)",
      "isOpenAccess": true,
      "inPmc": true,
      "authorString": "Bonner A, Gustafson O, Betteridge S, Pattison N, Watkinson PJ, Vollam S."
    },
    {
      "id": "d849070e-b3d5-452f-b600-419a9c8feb70",
      "doi": "10.12659/ajcr.951576",
      "url": "https://europepmc.org/article/PMC/13034717",
      "title": "Gastric Point-of-Care Ultrasound Diagnosis of Unexpected Gastrointestinal Dysfunction During ICU Ward Rounds: A Case Report.",
      "journal": "Am J Case Rep",
      "publishedAt": "2026-03-25",
      "sourceLanguage": "und",
      "license": "europepmc-oa",
      "specialty": "critical_care",
      "harvestedAt": "2026-06-12T14:38:28.122Z",
      "licenseVerified": true,
      "sourceId": "europe_pmc_oa",
      "pmcid": "PMC13034717",
      "pmid": "41880232",
      "searchQuery": "(intensive care OR critical care) AND (case report) AND (OPEN_ACCESS:Y)",
      "isOpenAccess": true,
      "inPmc": true,
      "authorString": "Theodosopoulou P, Fernandez-Vaquero MÁ, González-Delgado AD, Vives M."
    },
    {
      "id": "51b2eb2f-8af0-4739-b21a-f633fa827eec",
      "doi": "10.3389/fendo.2026.1820522",
      "url": "https://europepmc.org/article/PMC/13218953",
      "title": "Oral myiasis complicating endotracheal intubation in a diabetic patient: a case report.",
      "journal": "Front Endocrinol (Lausanne)",
      "publishedAt": "2026-05-15",
      "sourceLanguage": "und",
      "license": "europepmc-oa",
      "specialty": "critical_care",
      "harvestedAt": "2026-06-12T14:38:28.122Z",
      "licenseVerified": true,
      "sourceId": "europe_pmc_oa",
      "pmcid": "PMC13218953",
      "pmid": "42222065",
      "searchQuery": "(intensive care OR critical care) AND (case report) AND (OPEN_ACCESS:Y)",
      "isOpenAccess": true,
      "inPmc": true,
      "authorString": "Xiao Q, Zhao Y, Du J, Wang Y, Tang Q, Liang Z."
    },
    {
      "id": "55d02cdb-0359-4f19-a3c0-58d7e714fc3a",
      "url": "https://europepmc.org/article/PMC/13246020",
      "title": "Septic cardiomyopathy: a rare and life-threatening complication of small intestinal perforation: A case report",
      "journal": "Medicine (Baltimore)",
      "publishedAt": "2026-06-05",
      "sourceLanguage": "und",
      "license": "europepmc-oa",
      "specialty": "critical_care",
      "harvestedAt": "2026-06-12T14:38:28.122Z",
      "licenseVerified": true,
      "sourceId": "europe_pmc_oa",
      "pmcid": "PMC13246020",
      "searchQuery": "(intensive care OR critical care) AND (case report) AND (OPEN_ACCESS:Y)",
      "isOpenAccess": true,
      "inPmc": true,
      "authorString": "Wang F, Ma R, Luo Y, Ma D, Xiao J."
    },
    {
      "id": "4fa4ec9c-a56f-4b5e-9674-63fe82a89379",
      "doi": "10.3389/fmed.2026.1829484",
      "url": "https://europepmc.org/article/PMC/13216194",
      "title": "Transient complete heart block during early ambulation associated with thoracic epidural bupivacaine infusion in the intensive care unit: a case report.",
      "journal": "Front Med (Lausanne)",
      "publishedAt": "2026-05-14",
      "sourceLanguage": "und",
      "license": "europepmc-oa",
      "specialty": "critical_care",
      "harvestedAt": "2026-06-12T14:38:28.122Z",
      "licenseVerified": true,
      "sourceId": "europe_pmc_oa",
      "pmcid": "PMC13216194",
      "pmid": "42221122",
      "searchQuery": "(intensive care OR critical care) AND (case report) AND (OPEN_ACCESS:Y)",
      "isOpenAccess": true,
      "inPmc": true,
      "authorString": "Patel HB, Ho J, Blakely AM, Chertow DS."
    },
    {
      "id": "d4a08cd4-7d39-4830-8082-4bd2f80eea1d",
      "doi": "10.1016/j.idcr.2026.e02612",
      "url": "https://europepmc.org/article/PMC/13217840",
      "title": "VV-ECMO-supported management of severe ARDS secondary to melioidosis sepsis: A case report and concise review.",
      "journal": "IDCases",
      "publishedAt": "2026-05-15",
      "sourceLanguage": "und",
      "license": "europepmc-oa",
      "specialty": "critical_care",
      "harvestedAt": "2026-06-12T14:38:28.122Z",
      "licenseVerified": true,
      "sourceId": "europe_pmc_oa",
      "pmcid": "PMC13217840",
      "pmid": "42222019",
      "searchQuery": "(intensive care OR critical care) AND (case report) AND (OPEN_ACCESS:Y)",
      "isOpenAccess": true,
      "inPmc": true,
      "authorString": "Wang F, Xie C, Zhao M, Pan Y, Xie Y, Wang X, Zhu W, Xie Y."
    },
    {
      "id": "f5771b37-5b4a-4952-b96c-8abd10b1deb7",
      "doi": "10.1155/crps/5963356",
      "url": "https://europepmc.org/article/PMC/13239312",
      "title": "A 24-Year-Old Male Adult With a Severe Intellectual Developmental Disorder and Intractable Challenging Behaviors: A Case Report.",
      "journal": "Case Rep Psychiatry",
      "publishedAt": "2026-05-30",
      "sourceLanguage": "und",
      "license": "europepmc-oa",
      "specialty": "critical_care",
      "harvestedAt": "2026-06-12T14:38:28.122Z",
      "licenseVerified": true,
      "sourceId": "europe_pmc_oa",
      "pmcid": "PMC13239312",
      "pmid": "42256462",
      "searchQuery": "(intensive care OR critical care) AND (case report) AND (OPEN_ACCESS:Y)",
      "isOpenAccess": true,
      "inPmc": true,
      "authorString": "Guez E, Turin N, Doulou F, Beigheldrut Y, El Kossaifi P, Ferrari F, Levy-Soussan M, Cohen D, Giannitelli M."
    },
    {
      "id": "cefeefdb-38d3-4671-af61-104f7a51d1d9",
      "doi": "10.24908/pocusj.v11i01.19963",
      "url": "https://europepmc.org/article/PMC/13161771",
      "title": "Utilizing Cardiac POCUS for the Diagnosis of Dynamic Mitral Regurgitation.",
      "journal": "POCUS J",
      "publishedAt": "2026-04-22",
      "sourceLanguage": "und",
      "license": "europepmc-oa",
      "specialty": "critical_care",
      "harvestedAt": "2026-06-12T14:38:28.122Z",
      "licenseVerified": true,
      "sourceId": "europe_pmc_oa",
      "pmcid": "PMC13161771",
      "pmid": "42131557",
      "searchQuery": "(intensive care OR critical care) AND (case report) AND (OPEN_ACCESS:Y)",
      "isOpenAccess": true,
      "inPmc": true,
      "authorString": "Wee S, Aggarwal SK, Hoare D, Olusanya O."
    },
    {
      "id": "6870037c-a117-4910-9118-820db6e7ab04",
      "doi": "10.1002/ccr3.72786",
      "url": "https://europepmc.org/article/PMC/13240481",
      "title": "Beyond Vasospasm: Dual Milrinone and Balloon Angioplasty in Refractory Delayed Cerebral Ischemia Post-Subarachnoid Hemorrhage.",
      "journal": "Clin Case Rep",
      "publishedAt": "2026-05-24",
      "sourceLanguage": "und",
      "license": "europepmc-oa",
      "specialty": "critical_care",
      "harvestedAt": "2026-06-12T14:38:28.122Z",
      "licenseVerified": true,
      "sourceId": "europe_pmc_oa",
      "pmcid": "PMC13240481",
      "pmid": "42256960",
      "searchQuery": "(intensive care OR critical care) AND (case report) AND (OPEN_ACCESS:Y)",
      "isOpenAccess": true,
      "inPmc": true,
      "authorString": "Cardozo Gil P, Pozo Soto W, Sengoku Cadima A, Flores P, Botello Marin J, Averanga G, Hurtado Montaño R, Montalvo Flores N."
    },
    {
      "id": "d7441f86-5d18-4fca-bb21-7a89032f289f",
      "doi": "10.1016/j.rmcr.2026.102429",
      "url": "https://europepmc.org/article/PMC/13156767",
      "title": "A rare case report of acute respiratory distress syndrome secondary to pulmonary tuberculosis: Review of radiographic findings of pulmonary tuberculosis to enhance diagnosis accuracy.",
      "journal": "Respir Med Case Rep",
      "publishedAt": "2026-05-05",
      "sourceLanguage": "und",
      "license": "europepmc-oa",
      "specialty": "critical_care",
      "harvestedAt": "2026-06-12T14:38:28.122Z",
      "licenseVerified": true,
      "sourceId": "europe_pmc_oa",
      "pmcid": "PMC13156767",
      "pmid": "42112502",
      "searchQuery": "(intensive care OR critical care) AND (case report) AND (OPEN_ACCESS:Y)",
      "isOpenAccess": true,
      "inPmc": true,
      "authorString": "Boonyavarakul K, Wongjeeraphat T, Sriprasart T, Phoophiboon V."
    },
    {
      "id": "3ad2bbd3-0553-4a7e-9bff-7be605407ad4",
      "doi": "10.1111/nicc.70519",
      "url": "https://europepmc.org/article/PMC/13173626",
      "title": "The Ethical Tightrope of Physical and Environmental Restraint in ICU: A Balancing Act.",
      "journal": "Nurs Crit Care",
      "publishedAt": "2026-05-01",
      "sourceLanguage": "und",
      "license": "europepmc-oa",
      "specialty": "critical_care",
      "harvestedAt": "2026-06-12T14:38:28.122Z",
      "licenseVerified": true,
      "sourceId": "europe_pmc_oa",
      "pmcid": "PMC13173626",
      "pmid": "42132129",
      "searchQuery": "(intensive care OR critical care) AND (case report) AND (OPEN_ACCESS:Y)",
      "isOpenAccess": true,
      "inPmc": true,
      "authorString": "Bannon L, Meehan A, McEvoy N."
    },
    {
      "id": "b5b5165e-b576-4367-aa0f-8713040aa09c",
      "doi": "10.1016/j.ccrj.2026.100187",
      "url": "https://europepmc.org/article/PMC/13223824",
      "title": "Percutaneous dilatational tracheostomy in critical illness: A practice survey of intensivists in Australia and New Zealand.",
      "journal": "Crit Care Resusc",
      "publishedAt": "2026-05-22",
      "sourceLanguage": "und",
      "license": "europepmc-oa",
      "specialty": "critical_care",
      "harvestedAt": "2026-06-12T14:38:28.122Z",
      "licenseVerified": true,
      "sourceId": "europe_pmc_oa",
      "pmcid": "PMC13223824",
      "pmid": "42232733",
      "searchQuery": "(intensive care OR critical care) AND (case report) AND (OPEN_ACCESS:Y)",
      "isOpenAccess": true,
      "inPmc": true,
      "authorString": "Northcott MH, Subramaniam A, Jones D, Casamento A, Ali Abdelhamid Y, Bhonaghiri D, Sundararajan K."
    },
    {
      "id": "3fd0132f-9da7-4557-97bd-ca0880d90b0e",
      "url": "https://europepmc.org/article/PMC/13226843",
      "title": "Emergency open repair of war-related traumatic carotid artery injury caused by shrapnel in a resource-limited setting",
      "journal": "Trauma Case Rep",
      "publishedAt": "2026-05-25",
      "sourceLanguage": "und",
      "license": "europepmc-oa",
      "specialty": "critical_care",
      "harvestedAt": "2026-06-12T14:38:28.122Z",
      "licenseVerified": true,
      "sourceId": "europe_pmc_oa",
      "pmcid": "PMC13226843",
      "searchQuery": "(intensive care OR critical care) AND (case report) AND (OPEN_ACCESS:Y)",
      "isOpenAccess": true,
      "inPmc": true
    },
    {
      "id": "896f2fc8-7781-4f55-8d0b-e9eaac365d9c",
      "doi": "10.7759/cureus.107360",
      "url": "https://europepmc.org/article/PMC/13186607",
      "title": "Guillain-Barré Syndrome Following Seasonal Coronavirus (HCoV-229E) Infection: A Case Managed Without Intensive Care.",
      "journal": "Cureus",
      "publishedAt": "2026-04-19",
      "sourceLanguage": "und",
      "license": "europepmc-oa",
      "specialty": "critical_care",
      "harvestedAt": "2026-06-12T14:38:28.122Z",
      "licenseVerified": true,
      "sourceId": "europe_pmc_oa",
      "pmcid": "PMC13186607",
      "pmid": "42164222",
      "searchQuery": "(intensive care OR critical care) AND (case report) AND (OPEN_ACCESS:Y)",
      "isOpenAccess": true,
      "inPmc": true,
      "authorString": "Weldearegay G, Aghabekyan T, Arif A, Salvani J."
    },
    {
      "id": "581db48e-3977-442b-8a60-6b8b9b2a138d",
      "doi": "10.1186/s13256-026-06078-9",
      "url": "https://europepmc.org/article/PMC/13221768",
      "title": "Successful multistage surgical management of Boerhaave syndrome: a case report and review of the literature.",
      "journal": "J Med Case Rep",
      "publishedAt": "2026-05-01",
      "sourceLanguage": "und",
      "license": "europepmc-oa",
      "specialty": "critical_care",
      "harvestedAt": "2026-06-12T14:38:28.122Z",
      "licenseVerified": true,
      "sourceId": "europe_pmc_oa",
      "pmcid": "PMC13221768",
      "pmid": "42067928",
      "searchQuery": "(intensive care OR critical care) AND (case report) AND (OPEN_ACCESS:Y)",
      "isOpenAccess": true,
      "inPmc": true,
      "authorString": "Abdelgalil M, Tekle NF, Al Giurani FY, Iyoob A."
    },
    {
      "id": "eef3402b-56d8-4b4c-8185-14da167c2348",
      "doi": "10.2147/ijwh.s603663",
      "url": "https://europepmc.org/article/PMC/13170598",
      "title": "Perioperative Cardiac Arrest Complicated by Acute Pulmonary Edema Following Myomectomy: A Case Report from a Resource Limited Sitting.",
      "journal": "Int J Womens Health",
      "publishedAt": "2026-05-09",
      "sourceLanguage": "und",
      "license": "europepmc-oa",
      "specialty": "critical_care",
      "harvestedAt": "2026-06-12T14:38:28.122Z",
      "licenseVerified": true,
      "sourceId": "europe_pmc_oa",
      "pmcid": "PMC13170598",
      "pmid": "42137252",
      "searchQuery": "(intensive care OR critical care) AND (case report) AND (OPEN_ACCESS:Y)",
      "isOpenAccess": true,
      "inPmc": true,
      "authorString": "Hassan WM, Hassan RA, Tahajud OA, Hassan MA, Mohamed ZA, Ahmed MM."
    },
    {
      "id": "ecc3e73b-5bf7-40e2-b216-3861119be3c4",
      "doi": "10.1186/s13256-026-06046-3",
      "url": "https://europepmc.org/article/PMC/13248375",
      "title": "Hemoadsorption for refractory shock after amlodipine intoxication: a case report.",
      "journal": "J Med Case Rep",
      "publishedAt": "2026-04-25",
      "sourceLanguage": "und",
      "license": "europepmc-oa",
      "specialty": "critical_care",
      "harvestedAt": "2026-06-12T14:38:28.122Z",
      "licenseVerified": true,
      "sourceId": "europe_pmc_oa",
      "pmcid": "PMC13248375",
      "pmid": "42035130",
      "searchQuery": "(intensive care OR critical care) AND (case report) AND (OPEN_ACCESS:Y)",
      "isOpenAccess": true,
      "inPmc": true,
      "authorString": "Boavida L, Travassos S, Correia D, Silva D, de Jesus GN."
    },
    {
      "id": "07a95fab-21a1-4bc0-b5cb-0438f9294447",
      "doi": "10.1002/pan.70185",
      "url": "https://europepmc.org/article/PMC/13247627",
      "title": "Unplanned Post-Operative Pediatric Intensive Care Unit Admissions After Elective Upper Airway Procedures: A Retrospective Case-Control Study.",
      "journal": "Paediatr Anaesth",
      "publishedAt": "2026-04-11",
      "sourceLanguage": "und",
      "license": "europepmc-oa",
      "specialty": "critical_care",
      "harvestedAt": "2026-06-12T14:38:28.122Z",
      "licenseVerified": true,
      "sourceId": "europe_pmc_oa",
      "pmcid": "PMC13247627",
      "pmid": "41964314",
      "searchQuery": "(intensive care OR critical care) AND (case report) AND (OPEN_ACCESS:Y)",
      "isOpenAccess": true,
      "inPmc": true,
      "authorString": "Stancliff H, Basilious MM, Yoder LR, Krawiec C, Murphy T, Dalal PG."
    },
    {
      "id": "3a104e35-f3d8-4d1c-a2f1-d953a676b838",
      "doi": "10.1097/ms9.0000000000004975",
      "url": "https://europepmc.org/article/PMC/13236184",
      "title": "Xanthogranulomatous pyelonephritis complicating sepsis and abdominal compartment syndrome.",
      "journal": "Ann Med Surg (Lond)",
      "publishedAt": "2026-04-29",
      "sourceLanguage": "und",
      "license": "europepmc-oa",
      "specialty": "critical_care",
      "harvestedAt": "2026-06-12T14:38:28.122Z",
      "licenseVerified": true,
      "sourceId": "europe_pmc_oa",
      "pmcid": "PMC13236184",
      "pmid": "42254252",
      "searchQuery": "(intensive care OR critical care) AND (case report) AND (OPEN_ACCESS:Y)",
      "isOpenAccess": true,
      "inPmc": true,
      "authorString": "Zheng J, Chen Y, Zhang C, Shi J."
    },
    {
      "id": "8b5548ca-3f1b-4e9d-b0ca-44b20e525315",
      "doi": "10.4103/aca.aca_237_25",
      "url": "https://europepmc.org/article/PMC/13179076",
      "title": "Hypoplastic Left Heart Syndrome in a Neonate with Tracheoesophageal Fistula: An Anesthesiologist's Nightmare!",
      "journal": "Ann Card Anaesth",
      "publishedAt": "2026-04-15",
      "sourceLanguage": "und",
      "license": "europepmc-oa",
      "specialty": "critical_care",
      "harvestedAt": "2026-06-12T14:38:28.122Z",
      "licenseVerified": true,
      "sourceId": "europe_pmc_oa",
      "pmcid": "PMC13179076",
      "pmid": "41979316",
      "searchQuery": "(intensive care OR critical care) AND (case report) AND (OPEN_ACCESS:Y)",
      "isOpenAccess": true,
      "inPmc": true,
      "authorString": "Aravind M, Gupta A."
    },
    {
      "id": "02cc954f-ba7f-4e9f-89d9-c88158f23435",
      "doi": "10.3390/healthcare14101286",
      "url": "https://europepmc.org/article/PMC/13205619",
      "title": "Impact of Nurse-Performed Point-of-Care Ultrasound (PoCUS) in Adult Intensive Care: A Systematic Review.",
      "journal": "Healthcare (Basel)",
      "publishedAt": "2026-05-09",
      "sourceLanguage": "und",
      "license": "europepmc-oa",
      "specialty": "critical_care",
      "harvestedAt": "2026-06-12T14:38:28.122Z",
      "licenseVerified": true,
      "sourceId": "europe_pmc_oa",
      "pmcid": "PMC13205619",
      "pmid": "42194378",
      "searchQuery": "(intensive care OR critical care) AND (case report) AND (OPEN_ACCESS:Y)",
      "isOpenAccess": true,
      "inPmc": true,
      "authorString": "Abagnale M, Palazzo C, Zampetti N, De Filippo M, Citarella R, Abagnale FG, Cecere L, Limonti F, Gravante F."
    },
    {
      "id": "629157a5-b144-40d3-a28a-1d79ec1d1ac1",
      "doi": "10.2147/imcrj.s597732",
      "url": "https://europepmc.org/article/PMC/13111156",
      "title": "Severe Hypokalemia Complicated by Wernicke's Encephalopathy and Hypoxic-Ischemic Brain Injury in Pregnancy: A Case from a Resource-Limited ICU.",
      "journal": "Int Med Case Rep J",
      "publishedAt": "2026-04-21",
      "sourceLanguage": "und",
      "license": "europepmc-oa",
      "specialty": "critical_care",
      "harvestedAt": "2026-06-12T14:38:28.122Z",
      "licenseVerified": true,
      "sourceId": "europe_pmc_oa",
      "pmcid": "PMC13111156",
      "pmid": "42051410",
      "searchQuery": "(intensive care OR critical care) AND (case report) AND (OPEN_ACCESS:Y)",
      "isOpenAccess": true,
      "inPmc": true,
      "authorString": "Tahajud OA, Elmi AH, Ahmed OH, Ali HA."
    },
    {
      "id": "253a8041-dadd-4880-bb03-76627a4a8f4a",
      "doi": "10.1177/11795476261455925",
      "url": "https://europepmc.org/article/PMC/13201946",
      "title": "Hyperinflammatory Syndrome of Unknown Origin Complicated by Shock, DIC, Intracranial Hemorrhage and Spontaneous Splenic Rupture: A Case Report.",
      "journal": "Clin Med Insights Case Rep",
      "publishedAt": "2026-05-25",
      "sourceLanguage": "und",
      "license": "europepmc-oa",
      "specialty": "critical_care",
      "harvestedAt": "2026-06-12T14:38:28.122Z",
      "licenseVerified": true,
      "sourceId": "europe_pmc_oa",
      "pmcid": "PMC13201946",
      "pmid": "42205199",
      "searchQuery": "(intensive care OR critical care) AND (case report) AND (OPEN_ACCESS:Y)",
      "isOpenAccess": true,
      "inPmc": true,
      "authorString": "Serafinowicz Z, Gadomski J, Andruszkiewicz P, Zawadka M."
    },
    {
      "id": "b09af6d0-e3d8-4610-aab7-761de1d2e546",
      "doi": "10.7759/cureus.107289",
      "url": "https://europepmc.org/article/PMC/13182673",
      "title": "Aggressive Recurrent Bilateral Chylothorax Secondary to Follicular Lymphoma in an HIV-Positive Patient: A Case Report and Clinical Implications.",
      "journal": "Cureus",
      "publishedAt": "2026-04-18",
      "sourceLanguage": "und",
      "license": "europepmc-oa",
      "specialty": "critical_care",
      "harvestedAt": "2026-06-12T14:38:28.122Z",
      "licenseVerified": true,
      "sourceId": "europe_pmc_oa",
      "pmcid": "PMC13182673",
      "pmid": "42158761",
      "searchQuery": "(intensive care OR critical care) AND (case report) AND (OPEN_ACCESS:Y)",
      "isOpenAccess": true,
      "inPmc": true,
      "authorString": "Jagra AS, Ali R, Klukowicz A, Sharma HO, Miller R."
    }
  ]
}
